{
	"backtrace" : 4,
	"backtraceGraph" : 
	{
		"commands" : 
		[
			"add_custom_target",
			"include",
			"generate_messages",
			"add_dependencies"
		],
		"files" : 
		[
			"build/send_estimate_data/cmake/send_estimate_data-genmsg.cmake",
			"/opt/ros/noetic/share/genmsg/cmake/genmsg-extras.cmake",
			"send_estimate_data/CMakeLists.txt"
		],
		"nodes" : 
		[
			{
				"file" : 2
			},
			{
				"command" : 2,
				"file" : 2,
				"line" : 75,
				"parent" : 0
			},
			{
				"command" : 1,
				"file" : 1,
				"line" : 307,
				"parent" : 1
			},
			{
				"file" : 0,
				"parent" : 2
			},
			{
				"command" : 0,
				"file" : 0,
				"line" : 14,
				"parent" : 3
			},
			{
				"command" : 3,
				"file" : 0,
				"line" : 82,
				"parent" : 3
			},
			{
				"command" : 3,
				"file" : 0,
				"line" : 181,
				"parent" : 3
			},
			{
				"command" : 3,
				"file" : 0,
				"line" : 49,
				"parent" : 3
			},
			{
				"command" : 3,
				"file" : 0,
				"line" : 115,
				"parent" : 3
			},
			{
				"command" : 3,
				"file" : 0,
				"line" : 148,
				"parent" : 3
			}
		]
	},
	"dependencies" : 
	[
		{
			"backtrace" : 5,
			"id" : "send_estimate_data_generate_messages_eus::@88d42ac5d1b13be84670"
		},
		{
			"backtrace" : 6,
			"id" : "send_estimate_data_generate_messages_py::@88d42ac5d1b13be84670"
		},
		{
			"backtrace" : 7,
			"id" : "send_estimate_data_generate_messages_cpp::@88d42ac5d1b13be84670"
		},
		{
			"backtrace" : 8,
			"id" : "send_estimate_data_generate_messages_lisp::@88d42ac5d1b13be84670"
		},
		{
			"backtrace" : 9,
			"id" : "send_estimate_data_generate_messages_nodejs::@88d42ac5d1b13be84670"
		}
	],
	"id" : "send_estimate_data_generate_messages::@88d42ac5d1b13be84670",
	"name" : "send_estimate_data_generate_messages",
	"paths" : 
	{
		"build" : "send_estimate_data",
		"source" : "send_estimate_data"
	},
	"sources" : [],
	"type" : "UTILITY"
}
